MANIFEST.in
README.md
requirements.txt
setup.py
insales/__init__.py
insales/api.py
insales/composing.py
insales/connection.py
insales/parsing.py
pyinsales.egg-info/PKG-INFO
pyinsales.egg-info/SOURCES.txt
pyinsales.egg-info/dependency_links.txt
pyinsales.egg-info/requires.txt
pyinsales.egg-info/top_level.txt