Metadata-Version: 1.1
Name: pyinsales
Version: 0.6.4
Summary: InSales e-commerce platform API bindings
Home-page: https://github.com/nailxx/pyinsales
Author: Victor Nakoryakov
Author-email: nail.xx@gmail.com
License: MIT
Keywords: insales API bindings
Platform: UNKNOWN
Classifier: Development Status :: 4 - Beta
Classifier: License :: OSI Approved :: MIT License
Classifier: Intended Audience :: Developers
Classifier: Operating System :: OS Independent
Classifier: Programming Language :: Python
Classifier: Natural Language :: Russian
Classifier: Topic :: Utilities
